src/mux.v


module mux_module #(parameter n = 2, parameter WIDTH = 32)(
    input  wire [n-1:0] select,
    input  wire [(1<<n)*WIDTH-1:0] inp,  // Packed input vector
    output wire [WIDTH-1:0] out
);

    assign out = inp[select*WIDTH +: WIDTH];

endmodule



// module main;

// reg [1:0] select;
// reg [3:0] inp;
// output out;

// mux_module #(.n(2)) mux (.select(select),.inp(inp),.out(out));

// initial begin;
//     $display("select\t inp\t out");
//     $monitor("%b\t%b\t%b\t",select,inp,out);
//         inp = 4'b1010; select=2'b00; #10;
//         select=2'b11;#10;
//     $finish;
// end
// endmodule

src/register.v


module register_module #(parameter n=32)(
    input [n-1:0] in,
    input clk,
    input we,
    output [n-1:0] out,
    input reset
);

reg [n-1:0] register;

assign out = register;

always@(posedge clk or posedge reset) begin
    if(reset) begin
        register <= {n{1'b0}};
    end
    else
    if(we == 1'b1) begin
        register <= in;
    end
end




endmodule


// module main;

// reg [1:0] in;
// reg clk;
// reg we;
// wire [1:0] out;
// register_module register(.in(in),.clk(clk),.we(we),.out(out));
// initial begin
//     $display("in clk we out");
//     $monitor("%b %b %b\t %b",in,clk,we,out);
//         we=1;
//         clk=0; in=0; #10;
//         clk=1; #10;
//         clk=0; in=1; #10;
//         clk=1; #10;
//         clk=0; in=2; #10;
//         clk=1; #10;


//     $finish;
// end
// endmodule

src/alu.v


module alu_module(
    input [31:0] op1,
    input [31:0] op2,
    input [2:0] alu_sel,
    output [31:0] res,
    output zero
);

assign zero = (op1 == op2);


assign res = (alu_sel==3'b000) ? op1+op2 :
             (alu_sel==3'b001) ? op1-op2 : 
             (alu_sel==3'b010) ? op2 : //send only op2
             32'd0;
endmodule


// module main;

// reg [31:0] op1;
// reg [31:0] op2;
// reg [1:0] alu_sel;
// wire [31:0] res;
// wire zero;

// alu_module alu(.op1(op1),.op2(op2),.alu_sel(alu_sel),.res(res),.zero(zero));

// initial begin
//     $display("op1\t\t\t\t\t op2\t\t\t\t\t res\t\t\t\t\t zero");
//     $monitor("%b\t%b\t%b\t%b",op1,op2,res,zero);
//         alu_sel=2'b00;op1=32'd6;op2=32'd5; #10;

//     $finish;

// end


// endmodule

src/sign_extend.v


module sign_extend_module(
	input [31:0] inp,
	input [2:0] imm_src,
	output wire [31:0] out
);

// immsrc
// 000 - I
// 001 - S
// 010 - B
// 011 - J
// 100 - U
assign out = (imm_src == 3'b000) ? {{20{inp[31]}}, inp[31:20]} :
             (imm_src == 3'b001) ? {{20{inp[31]}}, inp[31:25], inp[11:7]} :
             (imm_src == 3'b010) ? {{20{inp[31]}}, inp[7], inp[30:25], inp[11:8], 1'b0} :
             (imm_src == 3'b011) ? {{12{inp[31]}}, inp[19:12], inp[20], inp[30:21], 1'b0} :
             (imm_src == 3'b100) ? {inp[31:12],12'b0} :
             32'd0;

 
endmodule

src/register_file.v


module register_file_module (
    input [4:0] a1,
    input [4:0] a2,
    input [4:0] a3,
    input [31:0] wd3,
    input we,
    input clk,
    input reset,
    output wire [31:0] rd1,
    output wire [31:0] rd2
);

reg [31:0] registers [0:31];


assign rd1 = registers[a1];
assign rd2 = registers[a2];

integer i;

always@(posedge clk or posedge reset) begin
    if(reset) begin

        // for(i=0;i<32;i++) //testbench //sw
        //     if(i==9)
        //         registers[i] <= 32'h00008000;
        //     else if(i==28)
        //         registers[i] <= 32'd5423;
        //     else
        //         registers[i] <= 32'd0;

        for(i=0;i<32;i++) //testbench beq
            if(i==4)
                registers[i] <= 32'h00008000;
            else if(i==5)
                registers[i] <= 32'd5423;
            else
                registers[i] <= 32'd0;
                
    end
    if(we && a3 != 5'd0) begin
        registers[a3] <= wd3;
    end
end


endmodule


// module main;

// reg [4:0] a1;
// reg [4:0] a2;
// reg [4:0] a3;
// reg [31:0] wd3;
// reg we;
// reg clk;
// wire [31:0] rd1;
// wire [31:0] rd2;


// register_file_module register_file(.a1(a1),.a2(a2),.a3(a3),.wd3(wd3),.we(we),.clk(clk),.rd1(rd1),.rd2(rd2));

// initial begin;
//     $display("a1\ta2\ta3\trd1\t\t\t\t\trd2");
//     $monitor("%b\t%b\t%b\t%b\t%b",a1,a2,a3,rd1,rd2);
//     a3=5'd9;wd3=32'b1000;we=1;clk=1; #10;
//     clk=0;we=0; #10;
//     a1=5'd9; #10;
//     $finish;
// end


// endmodule

src/memory_controller_tb.v


// module memory_controller(
//     output [3:0] address,
//     input clk,
//     output [3:0] data
// );

module memory_controller_module(
    input [23:0] addr,              // address 
    input we,                       // write enable
    input clk,                      // clk
    input [31:0] data_in,           // data in
    output wire [31:0] data_out,    // data out
    output wire op_r,               // output data ready
    input enable                    // start the r/w
);

reg [23:0] addr_reg=32'd0;
reg [3:0] counter=4'd0; //temporary to waste cycles simulating real case
reg [31:0] mem [0:15];
reg op_rr=0;
assign op_r = op_rr;
//just for the testbench purpose not synthesizable
initial begin
    // mem[24'd0]=32'hffc4a303; //load
    // mem[24'd0]=32'h0064a423; //store
    // mem[24'h00000c] = 32'h01020304;
    // mem[24'd0]=32'hfe420ae3; //beq
    mem[24'd0]=32'h0080016f; //jal
end


assign data_out = (!we && counter==4'd4) ? mem[addr_reg[3:0]] : 32'd0;

always@(posedge clk) begin
        

    if(counter==4'd4 || enable) begin
        counter <= 4'd0;
        op_rr <=0;
        addr_reg <= addr;
    end

    else
        counter <=counter+1;

    if(counter==4'd3) begin
        if(we)
            mem[addr_reg[3:0]] <= data_in;

        op_rr <=1;
    end

end
endmodule

//testbench

// `timescale 1 ns / 10 ps

// module main;
//     reg clk=0;
//     reg [23:0] addr=24'd4;              // address 
//     reg we=0;                       // write enable
//     reg [31:0] data_in=32'd0;           // data in
//     wire [31:0] data_out;    // data out
//     wire op_r;

//     reg [31:0] storage=32'd0;

//     parameter duration = 10000;

//     memory_controller_module uut(.clk(clk),.addr(addr),.we(we),.data_in(data_in),.data_out(data_out),.op_r(op_r));

//     always@(posedge clk) begin
//         if(op_r)
//             storage <= data_out;
//     end


//     always begin
//         #41.667
//         clk = ~clk;
//     end

//     initial begin
//         $dumpfile("memory_controller_tb.vcd");
//         $dumpvars(0,main);

//         #(duration)

//         $display("finished");
//         $finish();
//     end

// endmodule

src/cpu.v
// 9/7/25 rb
`include "register.v"
`include "alu.v"
`include "mux.v"
`include "memory_controller_tb.v"
`include "sign_extend.v"
`include "register_file.v"

module cpu_module(
    input wire pc_enable,
    input wire clk,
    input wire memsel_mux_select,
    input wire mem_write_enable,
    output wire mem_op_r,
    input wire ir_reg_enable,
    output wire [31:0] ir_reg_out,
    input wire rf_we,
    input wire regfile_mux_select,
    input wire [2:0] imm_src,
    input wire [1:0] opsel1_select,
    input wire [1:0] opsel2_select,
    output wire zero,
    input wire [2:0] alu_sel,
    input wire alu_reg_enable,
    input wire alu_reg_mux_select,
    input wire reset,
    input wire mem_enable,
    input wire old_pc_enable

    );

// wire pc_enable;
wire [31:0] pc_out;

// reg clk;
reg global_we=1;

//pc
register_module #(.n(32)) pc(
    .in(alu_reg_mux_out),
    .clk(clk),
    .we(pc_enable),
    .out(pc_out),
    .reset(reset)
    );

// wire old_pc_enable;
wire [31:0] old_pc_out;
//old pc
register_module #(.n(32)) old_pc(
    .in(pc_out),
    .clk(clk),
    .we(old_pc_enable),
    .out(old_pc_out),
    .reset(reset)
    );

// wire memsel_mux_select;
wire [31:0] memset_mux_out;
//memsel mux
assign memset_mux_out = (memsel_mux_select==1'b1) ? alu_reg_mux_out : pc_out;

// wire mem_write_enable;
wire [31:0] mem_data_out;
// wire mem_op_r;

//wire mem_enable
//memory module
memory_controller_module memory(
    .addr(memset_mux_out[23:0]),
    .we(mem_write_enable),
    .clk(clk),
    .data_in(rf_reg_rs2_out),
    .data_out(mem_data_out),
    .op_r(mem_op_r),
    .enable(mem_enable)
    );


//ir register
// wire ir_reg_enable;
// wire [31:0] ir_reg_out; //main decoding line
register_module ir_reg(
    .in(mem_data_out),
    .clk(clk),
    .we(ir_reg_enable),
    .out(ir_reg_out),
    .reset(reset)
    );

// wire rf_we;
//regfile mux
// wire regfile_mux_select;
wire [31:0] regfile_mux_out;
assign regfile_mux_out = (regfile_mux_select==1'b1) ? alu_reg_mux_out : mem_data_out;

wire [31:0] rs1_out;
wire [31:0] rs2_out; 

//register file
register_file_module regfile(
    .a1(ir_reg_out[19:15]),
    .a2(ir_reg_out[24:20]),
    .a3(ir_reg_out[11:7]),
    .we(rf_we),
    .wd3(regfile_mux_out), 
    .rd1(rs1_out),
    .rd2(rs2_out),
    .reset(reset)
    );

wire [31:0] rf_reg_rs1_out;
wire [31:0] rf_reg_rs2_out;

//register file register
register_module #(.n(32)) rf_reg1(
    .in(rs1_out),
    .clk(clk),
    .we(global_we),
    .out(rf_reg_rs1_out),
    .reset(reset)
    );

register_module #(.n(32)) rf_reg2(
    .in(rs2_out),
    .clk(clk),
    .we(global_we),
    .out(rf_reg_rs2_out),
    .reset(reset)
    );


//sign extender
// wire [2:0] imm_src;
wire [31:0] sign_extend_out;
sign_extend_module sign_extend(
    .inp(ir_reg_out),
    .imm_src(imm_src),
    .out(sign_extend_out)
    );

//opsel1 mux

wire [31:0] opsel1_mux_out;
// wire opsel1_select;
assign opsel1_mux_out = (opsel1_select==2'b00) ? rf_reg_rs1_out:
                        (opsel1_select==2'b01) ? pc_out:
                        (opsel1_select==2'b10) ? old_pc_out:
                        2'b00;

wire [31:0] opsel2_mux_out;
// wire [1:0] opsel2_select;

//opsel2 mux
assign opsel2_mux_out = (opsel2_select==2'b10) ? rf_reg_rs2_out:
                        (opsel2_select==2'b01) ? 32'd4 :
                        (opsel2_select==2'b00) ? sign_extend_out:
                        32'd0;


// wire zero;
// wire [2:0] alu_sel;
wire [31:0] alu_out;
alu_module alu1(
    .op1(opsel1_mux_out),
    .op2(opsel2_mux_out),
    .alu_sel(alu_sel),
    .res(alu_out),
    .zero(zero)
    );

// wire alu_reg_enable;
wire [31:0] alu_reg_out;

//alu reg
register_module #(.n(32)) alu_reg(
    .in(alu_out),
    .clk(clk),
    .we(alu_reg_enable),
    .out(alu_reg_out),
    .reset(reset)
    );


wire [31:0] alu_reg_mux_out;
// wire alu_reg_mux_select;

//alu reg mux
assign alu_reg_mux_out = (alu_reg_mux_select==1'b1) ? alu_out : alu_reg_out;



endmodule

src/cpu_tb.v

// 10/7/25
`timescale 1 ns / 10 ps
`include "cpu.v"

    
module main;
    reg pc_enable=0;
    reg clk=0;
    reg memsel_mux_select=0;
    reg mem_write_enable=0;
    wire mem_op_r;
    reg ir_reg_enable=0;
    wire [31:0] ir_reg_out;
    reg rf_we=0;
    reg regfile_mux_select=0;
    reg [2:0] imm_src=3'd0;
    reg [1:0] opsel1_select=2'b00;
    reg [1:0] opsel2_select=2'd0;
    wire zero;
    reg alu_reg_enable=0;
    reg alu_reg_mux_select=0;
    reg reset=0;
    reg mem_enable=0;
    wire [2:0] alu_sel;
    reg old_pc_enable=0;

    wire nclk;
    assign nclk = ~clk;


    wire [6:0] opcode;
    wire [14:12] func3;
    wire [31:24] func7;

    assign opcode = ir_reg_out[6:0];
    assign func3 = ir_reg_out[14:12];
    assign func7 = ir_reg_out[31:25]; 

    parameter duration=1000;

    cpu_module uut(
        .pc_enable(pc_enable),
        .clk(clk),
        .memsel_mux_select(memsel_mux_select),
        .mem_write_enable(mem_write_enable),
        .mem_op_r(mem_op_r),
        .ir_reg_enable(ir_reg_enable),
        .ir_reg_out(ir_reg_out),
        .rf_we(rf_we),
        .regfile_mux_select(regfile_mux_select),
        .imm_src(imm_src),
        .opsel1_select(opsel1_select),
        .opsel2_select(opsel2_select),
        .zero(zero),
        .alu_reg_enable(alu_reg_enable),
        .alu_reg_mux_select(alu_reg_mux_select),
        .reset(reset),
        .mem_enable(mem_enable),
        .alu_sel(alu_sel),
        .old_pc_enable(old_pc_enable)
        );


    reg [7:0] counter=4'd0;

    always begin
        #10
        clk = ~clk;
    end

    initial begin
        reset=1;
        #1
        reset=0;
        // counter=0;
        // #1
        // pc_enable=0;
        // memsel_mux_select=0;
        // mem_enable=1;
        // #8
        // mem_enable=0;
        // state=0;
        // nstate=0;
        // #70
        // ir_reg_enable=1;
        // #20
        // ir_reg_enable=0;
    end


    //alu src selection (alu control)
    assign alu_sel = (func3==3'b010 && opcode==7'b0000011) ? 3'b000 : //load lw
                     (func3==3'b010 && opcode==7'b0100011) ? 3'b000 : //store sw
                     (func3==3'b000 && opcode==7'b1100011) ? 3'b000 : //branch bne beq
                     (opcode==7'b1101111) ? 3'b000 : //jal
                     (opcode==7'b1100111) ? 3'b000 : //jalr (immediate type)
                     (opcode==7'b0110111) ? 3'b010 : //U type lui instruction
                     (opcode==7'b0010111) ? 3'b000 : //U type auipc instruction

                     (opcode==7'b0010011 && func3==3'b000) ? 3'b000 : //addi
                     
                     3'b000;

    reg [7:0] state=8'd0;
    reg [7:0] nstate=8'd0;


    
    always@(*) begin
        case(state)
            8'd0: nstate=8'd1;
            8'd1: nstate=8'd2;
            8'd2: begin
                if(mem_op_r==1) //wait for memory complete
                    nstate=8'd3;
                    ir_reg_enable=1;
                end
            8'd3: begin

                    case(opcode)
                        7'b0000011: begin
                            nstate=8'd4; //load type
                            imm_src=3'b000;
                        end
                        7'b0100011: begin
                            nstate=8'd7; //store type
                            imm_src=3'b001;
                        end
                        7'b1100011: begin
                            nstate=8'd9; //branch type
                            imm_src=3'b010;
                        end
                        7'b1101111: begin
                            nstate=8'd11; //jump type jal
                            imm_src=3'b011; 
                        end
                        7'b1100111: begin
                            nstate=8'd13; //jalr (immediate setting)
                            imm_src=3'b000;
                        end
                        7'b0110111: begin
                            nstate=8'd15; //U type lui instruction
                            imm_src=3'b100;
                        end
                        7'b0010111: begin
                            nstate=8'd16; //U type auipc instruction
                            imm_src=3'b100;
                        end
                        7'b0110011: begin //R type instruction
                            nstate=8'd17;
                        end
                        7'b0010011: begin //I type immediate 
                            nstate=8'd18;
                        end


                    endcase

                end
            //load type instruction
            8'd4: nstate=8'd5;
            8'd5: begin
                    if(mem_op_r==1) //wait for memory complete
                        nstate=8'd6;
                end
            8'd6: nstate=8'd0;

            //store type instruction
            8'd7: nstate=8'd8;
            8'd8:  begin
                    if(mem_op_r==1) //wait for memory complete
                        nstate=8'd0;
                end
            //end of store type

            //branch type instruction
            8'd9: nstate=8'd10;
            8'd10: nstate=8'd0;
            //jump type instruction
            8'd11: nstate=8'd12;
            8'd12: nstate=8'd0;
            //jalr immediate type instruction
            8'd13: nstate=8'd14;
            8'd14: nstate=8'd0;
            //U type lui instruction
            8'd15: nstate=8'd0;
            //U type auipc instruction
            8'd16: nstate=8'd0;
            //R type instruction
            8'd17: nstate=8'd0;
            //I type instruction other than lw
            8'd18: nstate=8'd0;

            default:nstate=8'd0;
        endcase
    end


    always@(posedge nclk) begin
        state <= nstate;

        case(state) 

            8'd1: //load from pc to memory
                begin
                // pc_enable=0;
                memsel_mux_select=0;
                mem_enable=1;
                // increment pc + 4
                opsel1_select=2'b01;
                opsel2_select=2'b01;
                alu_reg_mux_select=1;
                pc_enable=1;

                old_pc_enable=1; //for branch and jump instruction 14/7/25
                rf_we=0;
                end
            8'd2: //load from memory to ir
                begin
                    mem_enable=0;
                    imm_src=3'd0;

                    //disable increment pc + 4
                    opsel1_select=2'b00;
                    opsel2_select=2'b00;
                    alu_reg_mux_select=0;
                    pc_enable=0;

                    old_pc_enable=0;
                    
                end
            8'd3: //load from rf_file to rf_reg
                begin
                    ir_reg_enable=0;
                end

            // load type instruction
            8'd4: 
                begin
                    opsel1_select=2'b00;
                    opsel2_select=2'b00;

                    alu_reg_mux_select=1;
                    memsel_mux_select=1;
                    mem_enable=1;
                    regfile_mux_select=0;
                    rf_we=1;
                end
            8'd5: 
                    mem_enable=0;
            8'd6: 
                begin
                    alu_reg_mux_select=0;
                    memsel_mux_select=0;
                    rf_we=0;
                end
            //end of load type instruction

            //store type instruction
            8'd7:
                begin
                    opsel1_select=2'b00;
                    opsel2_select=2'b00;

                    alu_reg_mux_select=1;
                    memsel_mux_select=1;
                    mem_write_enable=1;
                    mem_enable=1;
                end
            8'd8:
                begin
                    mem_enable=0;
                end
            //end of store type instruction

            //branch type instruction
            8'd9:
                begin
                    opsel1_select=2'b00;
                    opsel2_select=2'b10;
                    pc_enable=0;
                end
            8'd10:
                begin
                    alu_reg_mux_select=1;
                    if(func3==3'b000 && zero) begin //beq
                        opsel1_select=2'b10;
                        opsel2_select=2'b00;
                        pc_enable=1;
                    end
                    else if(func3==3'b010 && !zero) begin //bne
                        opsel1_select=2'b10;
                        opsel2_select=2'b00;
                        pc_enable=1;
                    end
                    else begin
                        pc_enable=0;
                    end
                end
            //end of branch type instruction
            
            //jump type instruction
            8'd11:
                begin
                    regfile_mux_select=1;
                    opsel1_select=2'b10;
                    opsel2_select=2'b01;
                    alu_reg_mux_select=1; //better to remove the register itself not serving any purpose
                    rf_we=1;
                end
            8'd12:
                begin
                    opsel1_select=2'b10;
                    opsel2_select=2'b00;
                    alu_reg_mux_select=1;
                    rf_we=0;
                    pc_enable=1;
                end
            //end of jump type instruction

            //jalr instruction
            8'd13:
                begin
                    opsel1_select=2'b10;
                    opsel2_select=2'b01;
                    rf_we=1;
                    regfile_mux_select=1;
                    alu_reg_mux_select=1;
                end
            8'd14:
                begin
                    rf_we=0;

                    opsel1_select=2'b00;
                    opsel2_select=2'b00;
                    pc_enable=1;
                end
            //end of jalr instruction

            //U type lui instruction
            8'd15:
                begin
                    alu_reg_mux_select=1;
                    opsel2_select=2'b00;
                    rf_we=1;
                end
            //end of U type lui instruction
            //U type auipc instruction
            8'd16:
                begin
                    alu_reg_mux_select=1;
                    opsel1_select=2'b10;
                    opsel2_select=2'b00;
                    pc_enable=1;
                end
            //end of U type auipc instruction

            //R type instruction
            8'd17:
                begin
                    alu_reg_mux_select=1;
                    opsel1_select=2'b00;
                    opsel2_select=2'b10;
                    regfile_mux_select=1;
                    rf_we=1;
                end
            //end of R type instruction
            

            //I type instruction other than load type
            8'd18:
                begin
                    alu_reg_mux_select=1;
                    opsel1_select=2'b00;
                    opsel2_select=2'b00;
                    regfile_mux_select=1;
                    rf_we=1;
                end
            //end of I type instructions
            default:
                ;
        endcase
    end


    // always@(posedge nclk) begin
    //     counter <= counter+1;
    //     if(counter == 7'd3) begin // load from memory to ir
    //         ir_reg_enable=1;
    //     end
    //     if(counter == 7'd4) begin // select immsrc 
    //         ir_reg_enable=0;
    //         imm_src= 2'b00;

    //     end
    //     if(counter == 7'd5) begin //load from rf to rf_reg
    //         ir_reg_enable=0;
    //     end

    //     if(counter==7'd6) begin // load only alu reg
    //         alu_reg_enable = 1;
    //     end
    //     if(counter==7'd7) begin
    //         alu_reg_enable=0;
    //     end
    // end



    initial begin
        $dumpfile("cpu_tb.vcd");
        $dumpvars(0,main);

        #(duration)

        $finish();

    end
endmodule

src/cpu_tb.vcd
$date
	Tue Jul 15 16:44:40 2025
$end
$version
	Icarus Verilog
$end
$timescale
	10ps
$end
$scope module main $end
$var wire 1 ! nclk $end
$var wire 1 " zero $end
$var wire 7 # opcode [6:0] $end
$var wire 1 $ mem_op_r $end
$var wire 32 % ir_reg_out [31:0] $end
$var wire 8 & func7 [31:24] $end
$var wire 3 ' func3 [14:12] $end
$var wire 3 ( alu_sel [2:0] $end
$var reg 1 ) alu_reg_enable $end
$var reg 1 * alu_reg_mux_select $end
$var reg 1 + clk $end
$var reg 8 , counter [7:0] $end
$var reg 3 - imm_src [2:0] $end
$var reg 1 . ir_reg_enable $end
$var reg 1 / mem_enable $end
$var reg 1 0 mem_write_enable $end
$var reg 1 1 memsel_mux_select $end
$var reg 8 2 nstate [7:0] $end
$var reg 1 3 old_pc_enable $end
$var reg 2 4 opsel1_select [1:0] $end
$var reg 2 5 opsel2_select [1:0] $end
$var reg 1 6 pc_enable $end
$var reg 1 7 regfile_mux_select $end
$var reg 1 8 reset $end
$var reg 1 9 rf_we $end
$var reg 8 : state [7:0] $end
$scope module uut $end
$var wire 1 ) alu_reg_enable $end
$var wire 1 * alu_reg_mux_select $end
$var wire 3 ; alu_sel [2:0] $end
$var wire 1 + clk $end
$var wire 3 < imm_src [2:0] $end
$var wire 1 . ir_reg_enable $end
$var wire 1 / mem_enable $end
$var wire 1 0 mem_write_enable $end
$var wire 1 1 memsel_mux_select $end
$var wire 1 3 old_pc_enable $end
$var wire 2 = opsel1_select [1:0] $end
$var wire 2 > opsel2_select [1:0] $end
$var wire 1 6 pc_enable $end
$var wire 1 7 regfile_mux_select $end
$var wire 1 8 reset $end
$var wire 1 9 rf_we $end
$var wire 1 " zero $end
$var wire 32 ? sign_extend_out [31:0] $end
$var wire 32 @ rs2_out [31:0] $end
$var wire 32 A rs1_out [31:0] $end
$var wire 32 B rf_reg_rs2_out [31:0] $end
$var wire 32 C rf_reg_rs1_out [31:0] $end
$var wire 32 D regfile_mux_out [31:0] $end
$var wire 32 E pc_out [31:0] $end
$var wire 32 F opsel2_mux_out [31:0] $end
$var wire 32 G opsel1_mux_out [31:0] $end
$var wire 32 H old_pc_out [31:0] $end
$var wire 32 I memset_mux_out [31:0] $end
$var wire 1 $ mem_op_r $end
$var wire 32 J mem_data_out [31:0] $end
$var wire 32 K ir_reg_out [31:0] $end
$var wire 32 L alu_reg_out [31:0] $end
$var wire 32 M alu_reg_mux_out [31:0] $end
$var wire 32 N alu_out [31:0] $end
$var reg 1 O global_we $end
$scope module alu1 $end
$var wire 3 P alu_sel [2:0] $end
$var wire 32 Q op1 [31:0] $end
$var wire 32 R op2 [31:0] $end
$var wire 1 " zero $end
$var wire 32 S res [31:0] $end
$upscope $end
$scope module alu_reg $end
$var wire 1 + clk $end
$var wire 32 T in [31:0] $end
$var wire 1 8 reset $end
$var wire 1 ) we $end
$var wire 32 U out [31:0] $end
$var reg 32 V register [31:0] $end
$upscope $end
$scope module ir_reg $end
$var wire 1 + clk $end
$var wire 1 8 reset $end
$var wire 1 . we $end
$var wire 32 W out [31:0] $end
$var wire 32 X in [31:0] $end
$var reg 32 Y register [31:0] $end
$upscope $end
$scope module memory $end
$var wire 24 Z addr [23:0] $end
$var wire 1 + clk $end
$var wire 1 / enable $end
$var wire 1 $ op_r $end
$var wire 1 0 we $end
$var wire 32 [ data_out [31:0] $end
$var wire 32 \ data_in [31:0] $end
$var reg 24 ] addr_reg [23:0] $end
$var reg 4 ^ counter [3:0] $end
$var reg 1 _ op_rr $end
$upscope $end
$scope module old_pc $end
$var wire 1 + clk $end
$var wire 1 8 reset $end
$var wire 1 3 we $end
$var wire 32 ` out [31:0] $end
$var wire 32 a in [31:0] $end
$var reg 32 b register [31:0] $end
$upscope $end
$scope module pc $end
$var wire 1 + clk $end
$var wire 32 c in [31:0] $end
$var wire 1 8 reset $end
$var wire 1 6 we $end
$var wire 32 d out [31:0] $end
$var reg 32 e register [31:0] $end
$upscope $end
$scope module regfile $end
$var wire 5 f a1 [4:0] $end
$var wire 5 g a2 [4:0] $end
$var wire 5 h a3 [4:0] $end
$var wire 1 i clk $end
$var wire 32 j rd1 [31:0] $end
$var wire 32 k rd2 [31:0] $end
$var wire 1 8 reset $end
$var wire 32 l wd3 [31:0] $end
$var wire 1 9 we $end
$var integer 32 m i [31:0] $end
$upscope $end
$scope module rf_reg1 $end
$var wire 1 + clk $end
$var wire 32 n in [31:0] $end
$var wire 1 8 reset $end
$var wire 1 O we $end
$var wire 32 o out [31:0] $end
$var reg 32 p register [31:0] $end
$upscope $end
$scope module rf_reg2 $end
$var wire 1 + clk $end
$var wire 32 q in [31:0] $end
$var wire 1 8 reset $end
$var wire 1 O we $end
$var wire 32 r out [31:0] $end
$var reg 32 s register [31:0] $end
$upscope $end
$scope module sign_extend $end
$var wire 3 t imm_src [2:0] $end
$var wire 32 u inp [31:0] $end
$var wire 32 v out [31:0] $end
$upscope $end
$upscope $end
$upscope $end
$enddefinitions $end
#0
$dumpvars
b0 v
b0 u
b0 t
b0 s
b0 r
b0 q
b0 p
b0 o
b0 n
b100000 m
b0 l
b0 k
b0 j
zi
b0 h
b0 g
b0 f
b0 e
b0 d
b0 c
b0 b
b0 a
b0 `
0_
b0 ^
b0 ]
b0 \
b0 [
b0 Z
b0 Y
b0 X
b0 W
b0 V
b0 U
b0 T
b0 S
b0 R
b0 Q
b0 P
1O
b0 N
b0 M
b0 L
b0 K
b0 J
b0 I
b0 H
b0 G
b0 F
b0 E
b0 D
b0 C
b0 B
b0 A
b0 @
b0 ?
b0 >
b0 =
b0 <
b0 ;
b1 :
09
18
07
06
b0 5
b0 4
03
b10 2
01
00
0/
0.
b0 -
b0 ,
0+
0*
0)
b0 (
b0 '
b0 &
b0 %
0$
b0 #
1"
1!
$end
#100
08
#1000
b1 ^
0!
1+
#2000
1.
b10 :
b100 M
b100 c
b100 N
b100 S
b100 T
0"
b100 F
b100 R
13
16
1*
b1 5
b1 >
b1 4
b1 =
1/
1!
0+
#3000
b1000 M
b1000 c
b1000 N
b1000 S
b1000 T
1"
b100 G
b100 Q
b100 Z
b100 I
b100 E
b100 a
b100 d
b100 e
b0 ^
0!
1+
#4000
b0 M
b0 c
b0 F
b0 R
b0 N
b0 S
b0 T
1"
b0 G
b0 Q
03
06
0*
b0 5
b0 >
b0 4
b0 =
0/
1!
0+
#5000
b1 ^
0!
1+
#6000
1!
0+
#7000
b10 ^
0!
1+
#8000
1!
0+
#9000
b11 ^
0!
1+
#10000
1!
0+
#11000
b100000000000000101101111 D
b100000000000000101101111 l
b100000000000000101101111 J
b100000000000000101101111 X
b100000000000000101101111 [
b11 2
1$
1_
b100 ^
0!
1+
#12000
b11 :
1!
0+
#13000
b1000 N
b1000 S
b1000 T
0"
b1000 F
b1000 R
b1000 ?
b1000 v
b0 D
b0 l
b11 -
b11 <
b11 t
b1011 2
b0 J
b0 X
b0 [
b10 h
b1000 g
b1101111 #
b100000000000000101101111 %
b100000000000000101101111 K
b100000000000000101101111 W
b100000000000000101101111 Y
b100000000000000101101111 u
b100 ]
0$
0_
b0 ^
0!
1+
#14000
b1100 2
b1011 :
0.
1!
0+
#15000
b1 ^
0!
1+
#16000
b0 2
b1100 :
b100 D
b100 l
b100 N
b100 S
b100 T
b100 M
b100 c
b100 F
b100 R
19
1*
b1 5
b1 >
b10 4
b10 =
17
1!
0+
#17000
b10 ^
0!
1+
#18000
b1 2
b0 :
b1000 D
b1000 l
b1000 M
b1000 c
b1000 N
b1000 S
b1000 T
b1000 F
b1000 R
16
09
b0 5
b0 >
1!
0+
#19000
b1000 Z
b1000 I
b1000 E
b1000 a
b1000 d
b1000 e
b11 ^
0!
1+
#20000
b10 2
b1 :
1!
0+
#21000
bx J
bx X
bx [
1$
1_
b100 ^
0!
1+
#22000
1.
b11 2
b10 :
b1100 D
b1100 l
b1100 M
b1100 c
b1100 N
b1100 S
b1100 T
b100 F
b100 R
0"
b1000 G
b1000 Q
13
b1 5
b1 >
b1 4
b1 =
1/
1!
0+
#23000
b0x0x00 D
b0x0x00 l
bx0 ?
bx0 v
b0x0x00 M
b0x0x00 c
b0x0x00 N
b0x0x00 S
b0x0x00 T
b0x0 (
b0x0 ;
b0x0 P
b1100 G
b1100 Q
b1100 Z
b0 J
b0 X
b0 [
b1100 I
bx h
bx @
bx k
bx q
bx g
bx A
bx j
bx n
bx f
b0xxxxxxx &
bx '
bx #
b1100 E
b1100 a
b1100 d
b1100 e
b1000 H
b1000 `
b1000 b
bx %
bx K
bx W
bx Y
bx u
b1000 ]
0$
0_
b0 ^
0!
1+
#24000
b11 :
b0 D
b0 l
b0 M
b0 c
x"
bx F
bx R
bx N
bx S
bx T
b0 G
b0 Q
bx ?
bx v
03
06
0*
b0 5
b0 >
b0 4
b0 =
b0 -
b0 <
b0 t
0/
1!
0+
#25000
b0 F
b0 R
b0 (
b0 ;
b0 P
b0 ?
b0 v
bx G
bx Q
b0 h
b0 @
b0 k
b0 q
b0 g
b0 A
b0 j
b0 n
b0 f
b0 &
b0 '
b0 #
bx B
bx \
bx r
bx s
bx C
bx o
bx p
b0 %
b0 K
b0 W
b0 Y
b0 u
b1 ^
0!
1+
#26000
0.
1!
0+
#27000
b0 N
b0 S
b0 T
1"
b0 G
b0 Q
b0 C
b0 o
b0 p
b0 B
b0 \
b0 r
b0 s
b10 ^
0!
1+
#28000
1!
0+
#29000
b11 ^
0!
1+
#30000
1!
0+
#31000
bx J
bx X
bx [
1$
1_
b100 ^
0!
1+
#32000
1!
0+
#33000
b0 J
b0 X
b0 [
b1100 ]
0$
0_
b0 ^
0!
1+
#34000
1!
0+
#35000
b1 ^
0!
1+
#36000
1!
0+
#37000
b10 ^
0!
1+
#38000
1!
0+
#39000
b11 ^
0!
1+
#40000
1!
0+
#41000
bx J
bx X
bx [
1$
1_
b100 ^
0!
1+
#42000
1!
0+
#43000
b0 J
b0 X
b0 [
0$
0_
b0 ^
0!
1+
#44000
1!
0+
#45000
b1 ^
0!
1+
#46000
1!
0+
#47000
b10 ^
0!
1+
#48000
1!
0+
#49000
b11 ^
0!
1+
#50000
1!
0+
#51000
bx J
bx X
bx [
1$
1_
b100 ^
0!
1+
#52000
1!
0+
#53000
b0 J
b0 X
b0 [
0$
0_
b0 ^
0!
1+
#54000
1!
0+
#55000
b1 ^
0!
1+
#56000
1!
0+
#57000
b10 ^
0!
1+
#58000
1!
0+
#59000
b11 ^
0!
1+
#60000
1!
0+
#61000
bx J
bx X
bx [
1$
1_
b100 ^
0!
1+
#62000
1!
0+
#63000
b0 J
b0 X
b0 [
0$
0_
b0 ^
0!
1+
#64000
1!
0+
#65000
b1 ^
0!
1+
#66000
1!
0+
#67000
b10 ^
0!
1+
#68000
1!
0+
#69000
b11 ^
0!
1+
#70000
1!
0+
#71000
bx J
bx X
bx [
1$
1_
b100 ^
0!
1+
#72000
1!
0+
