src/final_memory_controller.v
//8/8/2025

`timescale 1 ns / 10 ps

module memory_controller_module(
    input [23:0] addr,              // address 
    input we,                       // write enable
    input clk,                      // clk
    input [31:0] data_in,           // data in
    output wire [31:0] data_out,    // data out
    output wire op_r,               // output data ready
    input enable,                   // start the r/w
    input [1:0] instr_mode,         //instruction mode

    //base address and offset registers
    input [23:0] flash_base_reg,
    input [23:0] boot_sector_offset,
    input [23:0] peripheral_base_offset,
    input [23:0] sram_base_offset,
    //extra fpga inputs

    output reg sram_ce,             // chip enable
    output reg flash_ce,            // nor flash enable
    output reg sck,                 // spi clock
    input sram_so,                  // serial output (from psram)
    input flash_so,                 // serial output (from flash)
    output wire sram_si,            // serial input (from psram)
    output wire flash_si,           // serial input (from flash)
    input reset                     // reset
    // output [6:0] c,                 // internal counter (temporary)
    // output ledg,                    // output green led (temporary)
    // output ledr                     // output reg led   (temporary)
);

localparam IDLE = 1'b0, BUSY = 1'b1;
reg state = IDLE;
reg [6:0] counter = 7'd0;
reg [7:0] cmd = 8'd0;
reg [31:0] data = 32'd0;
reg [31:0] le_data = 32'd0;
reg [1:0] memory_mode=0;

localparam read_cmd= 8'h03, write_cmd = 8'h02;
localparam sram_mode=2'b00, nor_fash_mode=2'b01, perpheral_mode=2'b10;
localparam word_mode=2'b00, byte_mode=2'b01, half_mode=2'b10;


//little endian converted and vice versa
always@(*) begin
    if(instr_mode==word_mode) begin // word mode
        le_data[31:24]=data_in[7:0];
        le_data[23:16]=data_in[15:8];
        le_data[15:8]=data_in[23:16];
        le_data[7:0]=data_in[31:24];
    end
    if(instr_mode==byte_mode) begin //byte mode
        le_data[7:0]=data_in[7:0];
        le_data[31:24]=8'd0;
        le_data[23:16]=8'd0;
        
    end
    if(instr_mode==half_mode) begin //half word mode
        le_data[15:8]=data_in[23:16];
        le_data[7:0]=data_in[31:24];
        le_data[31:24]=8'd0;
        le_data[23:16]=8'd0;
    end

end

//selection of memory mode
always@(*) begin
    if(addr > sram_base_offset) memory_mode=sram_mode;
    else if(addr >= peripheral_base_offset) memory_mode=perpheral_mode;
    else if(addr >= boot_sector_offset) memory_mode=nor_fash_mode;
end

//output data
assign data_out = (instr_mode==2'b00) ? ({data[7:0],data[15:8],data[23:16],data[31:24]}) : //word mode
                  (instr_mode==2'b01) ? ({24'b0,data[7:0]}): //byte mode
                  (instr_mode==2'b10) ? ({16'b0,data[7:0],data[15:8]}) : 32'd0; //half mode

//writing or reading
//sram si
assign sram_si = (memory_mode==sram_mode) ? (

                    (counter < 8) ? cmd[7-counter] : //cmd

                    (counter < 32) ? addr[31-counter] : //addr

                    (
                        (instr_mode==word_mode) ?
                        (
                            (counter < 64 && we) ? le_data[63-counter] : 1'b0
                        ) :
                        (instr_mode==byte_mode) ?
                        (
                            (counter < 56 && we) ? le_data[56-counter] : 1'b0
                        ) :
                        (instr_mode==half_mode) ?
                        (
                            (counter < 48 && we) ? le_data[48-counter] : 1'b0
                        ) : 1'b0

                        
                    )

                ) : 1'b0;

//flash si (no writing into flash)

wire [23:0] flash_addr_wire;
assign flash_addr_wire = (addr+flash_base_reg);
assign flash_si = (memory_mode==nor_fash_mode) ? (

                    (counter < 8) ? cmd[7-counter] : //cmd

                    (counter < 32) ? flash_addr_wire[31-counter] : //addr
                    1'b0
                    // (
                    //     (instr_mode==word_mode) ?
                    //     (
                    //         (counter < 64 && we) ? le_data[63-counter] : 1'b0
                    //     ) :
                    //     (instr_mode==byte_mode) ?
                    //     (
                    //         (counter < 56 && we) ? le_data[56-counter] : 1'b0
                    //     ) :
                    //     (instr_mode==half_mode) ?
                    //     (
                    //         (counter < 48 && we) ? le_data[48-counter] : 1'b0
                    //     ) : 1'b0

                        
                    // )

                ) : 1'b0;




always@(posedge clk or posedge reset) begin
    if(reset || !enable) begin
        sck<=1;
        sram_ce=0;
        flash_ce=1;
        counter<=0;
        state<=IDLE;
    end
    else if(enable) begin
        //sclk logic
        if(state==BUSY)
            if(sram_ce || ~flash_ce) sck <= ~sck;
            else sck <= 0;

        //read or write control

        if(state==IDLE) begin
            cmd <= (memory_mode==sram_mode) ? ((we) ? write_cmd : read_cmd) : //since both are same for flash and sram
                   (memory_mode==nor_fash_mode) ? ((we) ? write_cmd : read_cmd) :
                   (memory_mode==perpheral_mode) ? ((we) ? 8'b0 : 8'b0) : 8'd0; 

            if(memory_mode==sram_mode) sram_ce <= 1;
            if(memory_mode==flash_ce) flash_ce <= 0;
            //add peripherals in the future

            state <= BUSY;
            sck <= 0;
        end

        //counter control

        if((sram_ce && sck==1) || (flash_ce && sck==1)) begin
            if(instr_mode==word_mode) begin
                if(counter>=7'd63) begin
                    if(memory_mode==sram_mode) sram_ce <= 0;
                    if(memory_mode==nor_fash_mode) sram_ce <= 1;
                    counter <= 0;
                    state <= IDLE;
                end
                else counter <= counter + 1;
            end
            if(instr_mode==byte_mode) begin
                if(counter>=7'd47) begin
                    if(memory_mode==sram_mode) sram_ce <= 0;
                    if(memory_mode==nor_fash_mode) sram_ce <= 1;
                    counter <= 0;
                    state <= IDLE;
                end
                else counter <= counter + 1;
            end
            if(instr_mode==half_mode) begin
                if(counter>=7'd55) begin
                    if(memory_mode==sram_mode) sram_ce <= 0;
                    if(memory_mode==nor_fash_mode) sram_ce <= 1;
                    counter <= 0;
                    state <= IDLE;
                end
                else counter <= counter + 1;
            end

        end 

        //input control

        if(sck==0) begin
            if(instr_mode==word_mode) begin
                if(counter > 7'd31 && counter < 7'd64 && !we) begin
                    data[63-counter] <= (memory_mode==sram_mode) ? sram_so :
                                        (memory_mode==nor_fash_mode) ? flash_so : 1'b0;
                end
            end
            if(instr_mode==byte_mode) begin
                if(counter > 7'd31 && counter < 7'd48 && !we) begin
                    data[47-counter] <= (memory_mode==sram_mode) ? sram_so :
                                        (memory_mode==nor_fash_mode) ? flash_so : 1'b0;
                end
            end
            if(instr_mode==half_mode) begin
                if(counter > 7'd31 && counter < 7'd56 && !we) begin
                    data[55-counter] <= (memory_mode==sram_mode) ? sram_so :
                                        (memory_mode==nor_fash_mode) ? flash_so : 1'b0;
                end
            end
        end
    end
end

assign op_r = (memory_mode==sram_mode) ? 
                    ((counter == 7'd63 && sck == 1) ? 1'b1 : 1'b0) : 
              (memory_mode==nor_fash_mode) ? 
                    ((counter == 7'd63 && sck == 1) ? 1'b1 : 1'b0) :
              (memory_mode==perpheral_mode) ? 
                    (1'b0) :
              1'b0;


endmodule


module main;
        reg [23:0] addr=24'h0000aa;             
        reg we=1;                       
        reg clk=0;                      
        reg [31:0] data_in=32'habababab;           
        wire [31:0] data_out;    
        wire op_r;               
        reg enable=1;                   
        reg [1:0] instr_mode=2'b00;         
        //extra fpga inputs

        wire sram_ce;             
        wire flash_ce;            
        wire sck;                 
        wire sram_so;                  
        wire flash_so;                 
        wire sram_si;            
        wire flash_si;           
        reg reset=0;

        reg [23:0] flash_base_reg=24'h800000;
        reg [23:0] boot_sector_offset=24'd0;
        reg [23:0] peripheral_base_offset=24'd512;
        reg [23:0] sram_base_offset=24'd768;

    memory_controller_module uut(

        .addr(addr),             
        .we(we),                       
        .clk(clk),                      
        .data_in(data_in),           
        .data_out(data_out),    
        .op_r(op_r),               
        .enable(enable),                   
        .instr_mode(instr_mode),         
        .sram_ce(sram_ce),             
        .flash_ce(flash_ce),            
        .sck(sck),                 
        .sram_so(sram_so),                  
        .flash_so(flash_so),                 
        .sram_si(sram_si),            
        .flash_si(flash_si),           
        .reset(reset),
        .flash_base_reg(flash_base_reg),
        .boot_sector_offset(boot_sector_offset),
        .peripheral_base_offset(peripheral_base_offset),
        .sram_base_offset(sram_base_offset)
        );

    always begin
        #10
        clk = ~clk;
    end

    initial begin
        reset=1;
        #1
        reset=0;
    end

    initial begin
        $dumpfile("final_memory_controller.vcd");
        $dumpvars(0,main);

        #5000
        $finish();
    end


endmodule

src/final_memory_controller.vcd
$date
	Mon Aug 11 10:48:45 2025
$end
$version
	Icarus Verilog
$end
$timescale
	10ps
$end
$scope module main $end
$var wire 1 ! flash_so $end
$var wire 1 " sram_so $end
$var wire 1 # sram_si $end
$var wire 1 $ sram_ce $end
$var wire 1 % sck $end
$var wire 1 & op_r $end
$var wire 1 ' flash_si $end
$var wire 1 ( flash_ce $end
$var wire 32 ) data_out [31:0] $end
$var reg 24 * addr [23:0] $end
$var reg 24 + boot_sector_offset [23:0] $end
$var reg 1 , clk $end
$var reg 32 - data_in [31:0] $end
$var reg 1 . enable $end
$var reg 24 / flash_base_reg [23:0] $end
$var reg 2 0 instr_mode [1:0] $end
$var reg 24 1 peripheral_base_offset [23:0] $end
$var reg 1 2 reset $end
$var reg 24 3 sram_base_offset [23:0] $end
$var reg 1 4 we $end
$scope module uut $end
$var wire 24 5 addr [23:0] $end
$var wire 24 6 boot_sector_offset [23:0] $end
$var wire 1 , clk $end
$var wire 32 7 data_in [31:0] $end
$var wire 1 . enable $end
$var wire 24 8 flash_base_reg [23:0] $end
$var wire 1 ! flash_so $end
$var wire 2 9 instr_mode [1:0] $end
$var wire 24 : peripheral_base_offset [23:0] $end
$var wire 1 2 reset $end
$var wire 24 ; sram_base_offset [23:0] $end
$var wire 1 " sram_so $end
$var wire 1 4 we $end
$var wire 1 # sram_si $end
$var wire 1 & op_r $end
$var wire 1 ' flash_si $end
$var wire 24 < flash_addr_wire [23:0] $end
$var wire 32 = data_out [31:0] $end
$var reg 8 > cmd [7:0] $end
$var reg 7 ? counter [6:0] $end
$var reg 32 @ data [31:0] $end
$var reg 1 ( flash_ce $end
$var reg 32 A le_data [31:0] $end
$var reg 2 B memory_mode [1:0] $end
$var reg 1 % sck $end
$var reg 1 $ sram_ce $end
$var reg 1 C state $end
$upscope $end
$upscope $end
$enddefinitions $end
#0
$dumpvars
0C
b1 B
b10101011101010111010101110101011 A
b0 @
b0 ?
b0 >
b0 =
b100000000000000010101010 <
b1100000000 ;
b1000000000 :
b0 9
b100000000000000000000000 8
b10101011101010111010101110101011 7
b0 6
b10101010 5
14
b1100000000 3
12
b1000000000 1
b0 0
b100000000000000000000000 /
1.
b10101011101010111010101110101011 -
0,
b0 +
b10101010 *
b0 )
1(
0'
0&
1%
0$
0#
z"
z!
$end
#100
02
#1000
b1 ?
0%
1C
0(
b10 >
1,
#2000
0,
#3000
1%
1,
#4000
0,
#5000
0%
1,
#6000
0,
#7000
1%
1,
#8000
0,
#9000
0%
1,
#10000
0,
#11000
1%
1,
#12000
0,
#13000
0%
1,
#14000
0,
#15000
1%
1,
#16000
0,
#17000
0%
1,
#18000
0,
#19000
1%
1,
#20000
0,
#21000
0%
1,
#22000
0,
#23000
1%
1,
#24000
0,
#25000
0%
1,
#26000
0,
#27000
1%
1,
#28000
0,
#29000
0%
1,
#30000
0,
#31000
1%
1,
#32000
0,
#33000
0%
1,
#34000
0,
#35000
1%
1,
#36000
0,
#37000
0%
1,
#38000
0,
#39000
1%
1,
#40000
0,
#41000
0%
1,
#42000
0,
#43000
1%
1,
#44000
0,
#45000
0%
1,
#46000
0,
#47000
1%
1,
#48000
0,
#49000
0%
1,
#50000
0,
#51000
1%
1,
#52000
0,
#53000
0%
1,
#54000
0,
#55000
1%
1,
#56000
0,
#57000
0%
1,
#58000
0,
#59000
1%
1,
#60000
0,
#61000
0%
1,
#62000
0,
#63000
1%
1,
#64000
0,
#65000
0%
1,
#66000
0,
#67000
1%
1,
#68000
0,
#69000
0%
1,
#70000
0,
#71000
1%
1,
#72000
0,
#73000
0%
1,
#74000
0,
#75000
1%
1,
#76000
0,
#77000
0%
1,
#78000
0,
#79000
1%
1,
#80000
0,
#81000
0%
1,
#82000
0,
#83000
1%
1,
#84000
0,
#85000
0%
1,
#86000
0,
#87000
1%
1,
#88000
0,
#89000
0%
1,
#90000
0,
#91000
1%
1,
#92000
0,
#93000
0%
1,
#94000
0,
#95000
1%
1,
#96000
0,
#97000
0%
1,
#98000
0,
#99000
1%
1,
#100000
0,
#101000
0%
1,
#102000
0,
#103000
1%
1,
#104000
0,
#105000
0%
1,
#106000
0,
#107000
1%
1,
#108000
0,
#109000
0%
1,
#110000
0,
#111000
1%
1,
#112000
0,
#113000
0%
1,
#114000
0,
#115000
1%
1,
#116000
0,
#117000
0%
1,
#118000
0,
#119000
1%
1,
#120000
0,
#121000
0%
1,
#122000
0,
#123000
1%
1,
#124000
0,
#125000
0%
1,
#126000
0,
#127000
1%
1,
#128000
0,
#129000
0%
1,
#130000
0,
#131000
1%
1,
#132000
0,
#133000
0%
1,
#134000
0,
#135000
1%
1,
#136000
0,
#137000
0%
1,
#138000
0,
#139000
1%
1,
#140000
0,
#141000
0%
1,
#142000
0,
#143000
1%
1,
#144000
0,
#145000
0%
1,
#146000
0,
#147000
1%
1,
#148000
0,
#149000
0%
1,
#150000
0,
#151000
1%
1,
#152000
0,
#153000
0%
1,
#154000
0,
#155000
1%
1,
#156000
0,
#157000
0%
1,
#158000
0,
#159000
1%
1,
#160000
0,
#161000
0%
1,
#162000
0,
#163000
1%
1,
#164000
0,
#165000
0%
1,
#166000
0,
#167000
1%
1,
#168000
0,
#169000
0%
1,
#170000
0,
#171000
1%
1,
#172000
0,
#173000
0%
1,
#174000
0,
#175000
1%
1,
#176000
0,
#177000
0%
1,
#178000
0,
#179000
1%
1,
#180000
0,
#181000
0%
1,
#182000
0,
#183000
1%
1,
#184000
0,
#185000
0%
1,
#186000
0,
#187000
1%
1,
#188000
0,
#189000
0%
1,
#190000
0,
#191000
1%
1,
#192000
0,
#193000
0%
1,
#194000
0,
#195000
1%
1,
#196000
0,
#197000
0%
1,
#198000
0,
#199000
1%
1,
#200000
0,
#201000
0%
1,
#202000
0,
#203000
1%
1,
#204000
0,
#205000
0%
1,
#206000
0,
#207000
1%
1,
#208000
0,
#209000
0%
1,
#210000
0,
#211000
1%
1,
#212000
0,
#213000
0%
1,
#214000
0,
#215000
1%
1,
#216000
0,
#217000
0%
1,
#218000
0,
#219000
1%
1,
#220000
0,
#221000
0%
1,
#222000
0,
#223000
1%
1,
#224000
0,
#225000
0%
1,
#226000
0,
#227000
1%
1,
#228000
0,
#229000
0%
1,
#230000
0,
#231000
1%
1,
#232000
0,
#233000
0%
1,
#234000
0,
#235000
1%
1,
#236000
0,
#237000
0%
1,
#238000
0,
#239000
1%
1,
#240000
0,
#241000
0%
1,
#242000
0,
#243000
1%
1,
#244000
0,
#245000
0%
1,
#246000
0,
#247000
1%
1,
#248000
0,
#249000
0%
1,
#250000
0,
#251000
1%
1,
#252000
0,
#253000
0%
1,
#254000
0,
#255000
1%
1,
#256000
0,
#257000
0%
1,
#258000
0,
#259000
1%
1,
#260000
0,
#261000
0%
1,
#262000
0,
#263000
1%
1,
#264000
0,
#265000
0%
1,
#266000
0,
#267000
1%
1,
#268000
0,
#269000
0%
1,
#270000
0,
#271000
1%
1,
#272000
0,
#273000
0%
1,
#274000
0,
#275000
1%
1,
#276000
0,
#277000
0%
1,
#278000
0,
#279000
1%
1,
#280000
0,
#281000
0%
1,
#282000
0,
#283000
1%
1,
#284000
0,
#285000
0%
1,
#286000
0,
#287000
1%
1,
#288000
0,
#289000
0%
1,
#290000
0,
#291000
1%
1,
#292000
0,
#293000
0%
1,
#294000
0,
#295000
1%
1,
#296000
0,
#297000
0%
1,
#298000
0,
#299000
1%
1,
#300000
0,
#301000
0%
1,
#302000
0,
#303000
1%
1,
#304000
0,
#305000
0%
1,
#306000
0,
#307000
1%
1,
#308000
0,
#309000
0%
1,
#310000
0,
#311000
1%
1,
#312000
0,
#313000
0%
1,
#314000
0,
#315000
1%
1,
#316000
0,
#317000
0%
1,
#318000
0,
#319000
1%
1,
#320000
0,
#321000
0%
1,
#322000
0,
#323000
1%
1,
#324000
0,
#325000
0%
1,
#326000
0,
#327000
1%
1,
#328000
0,
#329000
0%
1,
#330000
0,
#331000
1%
1,
#332000
0,
#333000
0%
1,
#334000
0,
#335000
1%
1,
#336000
0,
#337000
0%
1,
#338000
0,
#339000
1%
1,
#340000
0,
#341000
0%
1,
#342000
0,
#343000
1%
1,
#344000
0,
#345000
0%
1,
#346000
0,
#347000
1%
1,
#348000
0,
#349000
0%
1,
#350000
0,
#351000
1%
1,
#352000
0,
#353000
0%
1,
#354000
0,
#355000
1%
1,
#356000
0,
#357000
0%
1,
#358000
0,
#359000
1%
1,
#360000
0,
#361000
0%
1,
#362000
0,
#363000
1%
1,
#364000
0,
#365000
0%
1,
#366000
0,
#367000
1%
1,
#368000
0,
#369000
0%
1,
#370000
0,
#371000
1%
1,
#372000
0,
#373000
0%
1,
#374000
0,
#375000
1%
1,
#376000
0,
#377000
0%
1,
#378000
0,
#379000
1%
1,
#380000
0,
#381000
0%
1,
#382000
0,
#383000
1%
1,
#384000
0,
#385000
0%
1,
#386000
0,
#387000
1%
1,
#388000
0,
#389000
0%
1,
#390000
0,
#391000
1%
1,
#392000
0,
#393000
0%
1,
#394000
0,
#395000
1%
1,
#396000
0,
#397000
0%
1,
#398000
0,
#399000
1%
1,
#400000
0,
#401000
0%
1,
#402000
0,
#403000
1%
1,
#404000
0,
#405000
0%
1,
#406000
0,
#407000
1%
1,
#408000
0,
#409000
0%
1,
#410000
0,
#411000
1%
1,
#412000
0,
#413000
0%
1,
#414000
0,
#415000
1%
1,
#416000
0,
#417000
0%
1,
#418000
0,
#419000
1%
1,
#420000
0,
#421000
0%
1,
#422000
0,
#423000
1%
1,
#424000
0,
#425000
0%
1,
#426000
0,
#427000
1%
1,
#428000
0,
#429000
0%
1,
#430000
0,
#431000
1%
1,
#432000
0,
#433000
0%
1,
#434000
0,
#435000
1%
1,
#436000
0,
#437000
0%
1,
#438000
0,
#439000
1%
1,
#440000
0,
#441000
0%
1,
#442000
0,
#443000
1%
1,
#444000
0,
#445000
0%
1,
#446000
0,
#447000
1%
1,
#448000
0,
#449000
0%
1,
#450000
0,
#451000
1%
1,
#452000
0,
#453000
0%
1,
#454000
0,
#455000
1%
1,
#456000
0,
#457000
0%
1,
#458000
0,
#459000
1%
1,
#460000
0,
#461000
0%
1,
#462000
0,
#463000
1%
1,
#464000
0,
#465000
0%
1,
#466000
0,
#467000
1%
1,
#468000
0,
#469000
0%
1,
#470000
0,
#471000
1%
1,
#472000
0,
#473000
0%
1,
#474000
0,
#475000
1%
1,
#476000
0,
#477000
0%
1,
#478000
0,
#479000
1%
1,
#480000
0,
#481000
0%
1,
#482000
0,
#483000
1%
1,
#484000
0,
#485000
0%
1,
#486000
0,
#487000
1%
1,
#488000
0,
#489000
0%
1,
#490000
0,
#491000
1%
1,
#492000
0,
#493000
0%
1,
#494000
0,
#495000
1%
1,
#496000
0,
#497000
0%
1,
#498000
0,
#499000
1%
1,
